mongo_schema_exporter/__init__.py
mongo_schema_exporter/cli.py
mongo_schema_exporter/schema_types.py
mongo_schema_exporter/schema_utils.py
mongo_schema_exporter-0.1.3.dist-info/METADATA
mongo_schema_exporter-0.1.3.dist-info/WHEEL
mongo_schema_exporter-0.1.3.dist-info/entry_points.txt
mongo_schema_exporter-0.1.3.dist-info/licenses/LICENSE
mongo_schema_exporter-0.1.3.dist-info/RECORD
