Metadata-Version: 2.4
Name: mongo_schema_exporter
Version: 0.1.3
Summary: Export MongoDB collection schemas into JSON Schema format
Project-URL: Homepage, https://github.com/barbuza/mongo_schema_exporter
Project-URL: Issues, https://github.com/barbuza/mongo_schema_exporter/issues
Author-email: Victor Kotseruba <barbuzaster@gmail.com>
License: MIT
License-File: LICENSE
Keywords: database,json-schema,mongodb,schema,validation
Classifier: Development Status :: 4 - Beta
Classifier: Intended Audience :: Developers
Classifier: License :: OSI Approved :: MIT License
Classifier: Programming Language :: Python :: 3
Classifier: Programming Language :: Python :: 3.13
Classifier: Topic :: Database
Classifier: Topic :: Software Development :: Libraries :: Python Modules
Requires-Python: >=3.13
Requires-Dist: argparse>=1.4.0
Requires-Dist: pymongo>=4.11.1
Requires-Dist: tqdm>=4.67.1
